Metadata-Version: 1.1
Name: cubicweb-vcrs
Version: 0.2.1
Summary: vcreview statistics
Home-page: http://www.cubicweb.org/project/cubicweb-vcrs
Author: LOGILAB S.A. (Paris, FRANCE)
Author-email: contact@logilab.fr
License: LGPL
Platform: UNKNOWN
Classifier: Environment :: Web Environment
Classifier: Framework :: CubicWeb
Classifier: Programming Language :: Python
Classifier: Programming Language :: JavaScript
